ncmpeg/__init__.py
ncmpeg/cli.py
ncmpeg-0.1.8.dist-info/METADATA
ncmpeg-0.1.8.dist-info/WHEEL
ncmpeg-0.1.8.dist-info/entry_points.txt
ncmpeg-0.1.8.dist-info/top_level.txt
ncmpeg-0.1.8.dist-info/RECORD
