Metadata-Version: 2.4
Name: ncmpeg
Version: 0.1.8
Summary: A terminal UI for FFmpeg built with Python and ncurses.
Author: Eren Öğrül
Author-email: Eren Öğrül <termapp@pm.me>
License: MIT
Requires-Python: >=3.8
Dynamic: author
Dynamic: requires-python
